{
"meta":{"launch_mode":"Train","name":"experiment","iteration_count":1000,"learn_metrics":[{"best_value":"Min","name":"RMSE"}],"test_sets":["test"],"test_metrics":[{"best_value":"Min","name":"RMSE"}],"learn_sets":["learn"]},
"iterations":[
{"learn":[35.41947528],"iteration":0,"passed_time":0.3520686672,"remaining_time":351.7165985,"test":[41.70910373]},
{"learn":[34.40876201],"iteration":1,"passed_time":0.4251526448,"remaining_time":212.1511698,"test":[40.51959131]},
{"learn":[33.4253921],"iteration":2,"passed_time":0.7670777249,"remaining_time":254.9254972,"test":[39.3580051]},
{"learn":[32.4817674],"iteration":3,"passed_time":1.095074755,"remaining_time":272.6736139,"test":[38.25886665]},
{"learn":[31.53536604],"iteration":4,"passed_time":1.10506967,"remaining_time":219.9088643,"test":[37.22261166]},
{"learn":[30.62033805],"iteration":5,"passed_time":1.117089777,"remaining_time":185.0645397,"test":[36.21830192]},
{"learn":[29.75711574],"iteration":6,"passed_time":1.438756841,"remaining_time":204.0979347,"test":[35.24484792]},
{"learn":[28.891897],"iteration":7,"passed_time":1.769721327,"remaining_time":219.4454445,"test":[34.27862449]},
{"learn":[28.06089702],"iteration":8,"passed_time":2.085797854,"remaining_time":229.6695193,"test":[33.3118442]},
{"learn":[27.26576255],"iteration":9,"passed_time":2.404478792,"remaining_time":238.0434004,"test":[32.44652574]},
{"learn":[26.50534637],"iteration":10,"passed_time":2.73157215,"remaining_time":245.5931687,"test":[31.539732]},
{"learn":[25.77400912],"iteration":11,"passed_time":3.069697275,"remaining_time":252.738409,"test":[31.00288577]},
{"learn":[25.06007165],"iteration":12,"passed_time":3.397797537,"remaining_time":257.9712438,"test":[30.20454468]},
{"learn":[24.33968785],"iteration":13,"passed_time":3.721860553,"remaining_time":262.1253218,"test":[29.3835447]},
{"learn":[23.64162418],"iteration":14,"passed_time":4.023448842,"remaining_time":264.2064739,"test":[28.57568487]},
{"learn":[22.96130305],"iteration":15,"passed_time":4.333723081,"remaining_time":266.5239695,"test":[27.80430458]},
{"learn":[22.29690056],"iteration":16,"passed_time":4.633905519,"remaining_time":267.9487721,"test":[27.05537969]},
{"learn":[21.65734299],"iteration":17,"passed_time":4.943361775,"remaining_time":269.687848,"test":[26.32962787]},
{"learn":[21.03888579],"iteration":18,"passed_time":5.266321934,"remaining_time":271.9085167,"test":[25.59983343]},
{"learn":[20.44348183],"iteration":19,"passed_time":5.577178134,"remaining_time":273.2817285,"test":[24.91370982]},
{"learn":[19.85279454],"iteration":20,"passed_time":5.876624587,"remaining_time":273.9626414,"test":[24.26461305]},
{"learn":[19.29778274],"iteration":21,"passed_time":6.181199228,"remaining_time":274.782402,"test":[23.64241814]},
{"learn":[18.74108455],"iteration":22,"passed_time":6.499927504,"remaining_time":276.1056162,"test":[23.00558165]},
{"learn":[18.22841453],"iteration":23,"passed_time":6.816948228,"remaining_time":277.2225613,"test":[22.37999878]},
{"learn":[17.7029449],"iteration":24,"passed_time":7.133502642,"remaining_time":278.206603,"test":[21.78586935]},
{"learn":[17.19874897],"iteration":25,"passed_time":7.443520245,"remaining_time":278.8457199,"test":[21.20803215]},
{"learn":[16.71272741],"iteration":26,"passed_time":7.744965154,"remaining_time":279.1055961,"test":[20.65311656]},
{"learn":[16.24302163],"iteration":27,"passed_time":8.056634504,"remaining_time":279.6803121,"test":[20.12592759]},
{"learn":[15.77457598],"iteration":28,"passed_time":8.065185534,"remaining_time":270.0446605,"test":[19.64106462]},
{"learn":[15.33617804],"iteration":29,"passed_time":8.211718227,"remaining_time":265.5122227,"test":[19.19139932]},
{"learn":[14.89946745],"iteration":30,"passed_time":8.534028349,"remaining_time":266.7572087,"test":[18.68872829]},
{"learn":[14.47016232],"iteration":31,"passed_time":8.544244526,"remaining_time":258.4633969,"test":[18.18292906]},
{"learn":[14.05371771],"iteration":32,"passed_time":8.850226406,"remaining_time":259.3384526,"test":[17.70876398]},
{"learn":[13.66246809],"iteration":33,"passed_time":9.158840093,"remaining_time":260.2188097,"test":[17.27671457]},
{"learn":[13.27940563],"iteration":34,"passed_time":9.477343053,"remaining_time":261.303887,"test":[16.83185289]},
{"learn":[12.90055588],"iteration":35,"passed_time":9.790612115,"remaining_time":262.1708355,"test":[16.40075832]},
{"learn":[12.5419245],"iteration":36,"passed_time":10.09246757,"remaining_time":262.6769262,"test":[15.99893631]},
{"learn":[12.19123273],"iteration":37,"passed_time":10.39925227,"remaining_time":263.2652811,"test":[15.60914749]},
{"learn":[11.84946824],"iteration":38,"passed_time":10.68955594,"remaining_time":263.4016219,"test":[15.21601693]},
{"learn":[11.52572765],"iteration":39,"passed_time":10.98739398,"remaining_time":263.6974556,"test":[14.83604393]},
{"learn":[11.19879565],"iteration":40,"passed_time":11.28482812,"remaining_time":263.9548822,"test":[14.46761226]},
{"learn":[10.88595165],"iteration":41,"passed_time":11.59049392,"remaining_time":264.373647,"test":[14.10308628]},
{"learn":[10.57181588],"iteration":42,"passed_time":11.89421548,"remaining_time":264.7154469,"test":[13.74006866]},
{"learn":[10.28471259],"iteration":43,"passed_time":12.19874968,"remaining_time":265.0455612,"test":[13.44386536]},
{"learn":[9.986299405],"iteration":44,"passed_time":12.20860823,"remaining_time":259.0937969,"test":[13.1059659]},
{"learn":[9.708294295],"iteration":45,"passed_time":12.50743578,"remaining_time":259.3933421,"test":[12.7835227]},
{"learn":[9.437276165],"iteration":46,"passed_time":12.80816954,"remaining_time":259.706076,"test":[12.47390122]},
{"learn":[9.171128252],"iteration":47,"passed_time":13.10929651,"remaining_time":260.0010475,"test":[12.16219164]},
{"learn":[8.915788611],"iteration":48,"passed_time":13.40870066,"remaining_time":260.2382516,"test":[11.8745254]},
{"learn":[8.674444937],"iteration":49,"passed_time":13.7127099,"remaining_time":260.5414882,"test":[11.58996908]},
{"learn":[8.437596043],"iteration":50,"passed_time":14.01480169,"remaining_time":260.7852314,"test":[11.29059056]},
{"learn":[8.20625589],"iteration":51,"passed_time":14.31359732,"remaining_time":260.9478896,"test":[11.01959951]},
{"learn":[7.980862645],"iteration":52,"passed_time":14.6151271,"remaining_time":261.1419879,"test":[10.7762735]},
{"learn":[7.75734872],"iteration":53,"passed_time":14.74762125,"remaining_time":258.356476,"test":[10.50234439]},
{"learn":[7.538828427],"iteration":54,"passed_time":15.05992562,"remaining_time":258.7569039,"test":[10.25828194]},
{"learn":[7.325663051],"iteration":55,"passed_time":15.36449007,"remaining_time":259.0014041,"test":[10.01695674]},
{"learn":[7.121209871],"iteration":56,"passed_time":15.66459155,"remaining_time":259.1528041,"test":[9.771112327]},
{"learn":[6.921717147],"iteration":57,"passed_time":15.96767262,"remaining_time":259.3370278,"test":[9.572043604]},
{"learn":[6.731209971],"iteration":58,"passed_time":16.2688625,"remaining_time":259.4745696,"test":[9.34784758]},
{"learn":[6.547702264],"iteration":59,"passed_time":16.57306318,"remaining_time":259.6446565,"test":[9.134115819]},
{"learn":[6.368417738],"iteration":60,"passed_time":16.87525349,"remaining_time":259.7682463,"test":[8.931716827]},
{"learn":[6.194562851],"iteration":61,"passed_time":17.18152301,"remaining_time":259.9398159,"test":[8.732577952]},
{"learn":[6.022358127],"iteration":62,"passed_time":17.4831176,"remaining_time":260.0266856,"test":[8.548164408]},
{"learn":[5.855109204],"iteration":63,"passed_time":17.78365398,"remaining_time":260.0859394,"test":[8.36391821]},
{"learn":[5.694790581],"iteration":64,"passed_time":18.08667737,"remaining_time":260.1698976,"test":[8.172819211]},
{"learn":[5.54330222],"iteration":65,"passed_time":18.40535531,"remaining_time":260.4636645,"test":[7.995049573]},
{"learn":[5.39022075],"iteration":66,"passed_time":18.47332642,"remaining_time":257.2479634,"test":[7.807515766]},
{"learn":[5.247591704],"iteration":67,"passed_time":18.78068522,"remaining_time":257.4058621,"test":[7.649205795]},
{"learn":[5.102828268],"iteration":68,"passed_time":18.84656132,"remaining_time":254.2920085,"test":[7.482912697]},
{"learn":[4.967980257],"iteration":69,"passed_time":19.16158671,"remaining_time":254.5753663,"test":[7.320314989]},
{"learn":[4.83680878],"iteration":70,"passed_time":19.46407924,"remaining_time":254.6778819,"test":[7.159427584]},
{"learn":[4.710289168],"iteration":71,"passed_time":19.77220879,"remaining_time":254.8418022,"test":[6.996129099]},
{"learn":[4.583224492],"iteration":72,"passed_time":20.07918696,"remaining_time":254.9781687,"test":[6.847032229]},
{"learn":[4.463044714],"iteration":73,"passed_time":20.38354403,"remaining_time":255.0697537,"test":[6.704615132]},
{"learn":[4.345599163],"iteration":74,"passed_time":20.68553929,"remaining_time":255.1216513,"test":[6.5645514]},
{"learn":[4.230577039],"iteration":75,"passed_time":20.98389475,"remaining_time":255.1199835,"test":[6.439795324]},
{"learn":[4.12061686],"iteration":76,"passed_time":21.28255686,"remaining_time":255.1142855,"test":[6.303901747]},
{"learn":[4.014259413],"iteration":77,"passed_time":21.58598355,"remaining_time":255.1573953,"test":[6.192344742]},
{"learn":[3.908527594],"iteration":78,"passed_time":21.59657565,"remaining_time":251.7777996,"test":[6.065994226]},
{"learn":[3.811471445],"iteration":79,"passed_time":21.89963181,"remaining_time":251.8457658,"test":[5.951078122]},
{"learn":[3.716124489],"iteration":80,"passed_time":22.2048674,"remaining_time":251.929298,"test":[5.83432112]},
{"learn":[3.622391131],"iteration":81,"passed_time":22.50702442,"remaining_time":251.9688832,"test":[5.723482636]},
{"learn":[3.531595476],"iteration":82,"passed_time":22.80812947,"remaining_time":251.9886111,"test":[5.613988047]},
{"learn":[3.441713314],"iteration":83,"passed_time":23.11454039,"remaining_time":252.0585595,"test":[5.506064587]},
{"learn":[3.355578207],"iteration":84,"passed_time":23.41497252,"remaining_time":252.0552924,"test":[5.408860868]},
{"learn":[3.270838642],"iteration":85,"passed_time":23.71280525,"remaining_time":252.0174883,"test":[5.304054726]},
{"learn":[3.191060824],"iteration":86,"passed_time":24.01253182,"remaining_time":251.993581,"test":[5.206669972]},
{"learn":[3.112597605],"iteration":87,"passed_time":24.03206199,"remaining_time":249.0595515,"test":[5.106288306]},
{"learn":[3.036441863],"iteration":88,"passed_time":24.33594788,"remaining_time":249.1016687,"test":[5.015791987]},
{"learn":[2.965345818],"iteration":89,"passed_time":24.63631268,"remaining_time":249.1004948,"test":[4.933241152]},
{"learn":[2.895959609],"iteration":90,"passed_time":24.93969218,"remaining_time":249.1228592,"test":[4.843840572]},
{"learn":[2.828874588],"iteration":91,"passed_time":25.24021279,"remaining_time":249.1099263,"test":[4.801341476]},
{"learn":[2.763529168],"iteration":92,"passed_time":25.54239059,"remaining_time":249.1069706,"test":[4.714568207]},
{"learn":[2.697750832],"iteration":93,"passed_time":25.54587975,"remaining_time":246.2187985,"test":[4.630186142]},
{"learn":[2.635045645],"iteration":94,"passed_time":25.85240762,"remaining_time":246.2781989,"test":[4.555133681]},
{"learn":[2.575070914],"iteration":95,"passed_time":26.16652966,"remaining_time":246.4014876,"test":[4.478362362]},
{"learn":[2.518483876],"iteration":96,"passed_time":26.4739232,"remaining_time":246.4531201,"test":[4.405907025]},
{"learn":[2.462364759],"iteration":97,"passed_time":26.7749104,"remaining_time":246.438461,"test":[4.337355638]},
{"learn":[2.40911043],"iteration":98,"passed_time":27.07583256,"remaining_time":246.4174256,"test":[4.269653661]},
{"learn":[2.356898152],"iteration":99,"passed_time":27.38062081,"remaining_time":246.4255873,"test":[4.202160957]},
{"learn":[2.308039338],"iteration":100,"passed_time":27.68703425,"remaining_time":246.4420177,"test":[4.146473741]},
{"learn":[2.259572241],"iteration":101,"passed_time":27.69034573,"remaining_time":243.783632,"test":[4.092457507]},
{"learn":[2.211976558],"iteration":102,"passed_time":27.6932859,"remaining_time":241.1735675,"test":[4.028481871]},
{"learn":[2.167523922],"iteration":103,"passed_time":28.0018798,"remaining_time":241.2469644,"test":[3.97640427]},
{"learn":[2.123759452],"iteration":104,"passed_time":28.2927937,"remaining_time":241.1623844,"test":[3.917618188]},
{"learn":[2.082871107],"iteration":105,"passed_time":28.59968692,"remaining_time":241.2086803,"test":[3.850346832]},
{"learn":[2.042858971],"iteration":106,"passed_time":28.90265259,"remaining_time":241.2155959,"test":[3.795040702]},
{"learn":[2.006424149],"iteration":107,"passed_time":29.2092826,"remaining_time":241.2470378,"test":[3.745371707]},
{"learn":[1.969482294],"iteration":108,"passed_time":29.50799398,"remaining_time":241.2075471,"test":[3.692682262]},
{"learn":[1.93342364],"iteration":109,"passed_time":29.51391825,"remaining_time":238.7944295,"test":[3.640502098]},
{"learn":[1.899051424],"iteration":110,"passed_time":29.82151182,"remaining_time":238.8407569,"test":[3.599594634]},
{"learn":[1.8664122],"iteration":111,"passed_time":30.13556776,"remaining_time":238.9320015,"test":[3.557735709]},
{"learn":[1.834894495],"iteration":112,"passed_time":30.44987497,"remaining_time":239.0180451,"test":[3.504357804]},
{"learn":[1.804439114],"iteration":113,"passed_time":30.75592535,"remaining_time":239.0328935,"test":[3.459011659]},
{"learn":[1.775820559],"iteration":114,"passed_time":31.0617147,"remaining_time":239.0401522,"test":[3.417100446]},
{"learn":[1.747602899],"iteration":115,"passed_time":31.36764982,"remaining_time":239.0431245,"test":[3.383731814]},
{"learn":[1.721086409],"iteration":116,"passed_time":31.67160658,"remaining_time":239.0258856,"test":[3.34748602]},
{"learn":[1.695232298],"iteration":117,"passed_time":31.97697652,"remaining_time":239.01435,"test":[3.309850466]},
{"learn":[1.669740741],"iteration":118,"passed_time":31.98144542,"remaining_time":236.7701968,"test":[3.279115097]},
{"learn":[1.644645272],"iteration":119,"passed_time":31.99949208,"remaining_time":234.6629419,"test":[3.246279647]},
{"learn":[1.62181855],"iteration":120,"passed_time":32.30321291,"remaining_time":234.6654889,"test":[3.20987884]},
{"learn":[1.600384894],"iteration":121,"passed_time":32.61650269,"remaining_time":234.73188,"test":[3.174424929]},
{"learn":[1.579525278],"iteration":122,"passed_time":32.68484135,"remaining_time":233.0455761,"test":[3.141728989]},
{"learn":[1.559385548],"iteration":123,"passed_time":32.75866489,"remaining_time":231.4241165,"test":[3.108678134]},
{"learn":[1.54012024],"iteration":124,"passed_time":33.08082088,"remaining_time":231.5657462,"test":[3.077473437]},
{"learn":[1.521685507],"iteration":125,"passed_time":33.3910611,"remaining_time":231.6173603,"test":[3.033917832]},
{"learn":[1.503592363],"iteration":126,"passed_time":33.69683001,"remaining_time":231.6325401,"test":[3.041188702]},
{"learn":[1.486972699],"iteration":127,"passed_time":34.00745015,"remaining_time":231.6757542,"test":[3.011296625]},
{"learn":[1.471284223],"iteration":128,"passed_time":34.31415106,"remaining_time":231.68702,"test":[2.987188356]},
{"learn":[1.456055324],"iteration":129,"passed_time":34.61829101,"remaining_time":231.6762552,"test":[2.958353553]},
{"learn":[1.441245828],"iteration":130,"passed_time":34.7534739,"remaining_time":230.54022,"test":[2.932776955]},
{"learn":[1.42699611],"iteration":131,"passed_time":34.77129519,"remaining_time":228.6476078,"test":[2.902971626]},
{"learn":[1.413673208],"iteration":132,"passed_time":34.77768267,"remaining_time":226.7086532,"test":[2.876748977]},
{"learn":[1.401003825],"iteration":133,"passed_time":35.08330671,"remaining_time":226.732415,"test":[2.863874783]},
{"learn":[1.387931538],"iteration":134,"passed_time":35.12033565,"remaining_time":225.0302988,"test":[2.842038818]},
{"learn":[1.376483997],"iteration":135,"passed_time":35.44920091,"remaining_time":225.2066881,"test":[2.820967602]},
{"learn":[1.365428401],"iteration":136,"passed_time":35.45889901,"remaining_time":223.3651813,"test":[2.79941541]},
{"learn":[1.354531275],"iteration":137,"passed_time":35.76193522,"remaining_time":223.3825229,"test":[2.781853691]},
{"learn":[1.34369628],"iteration":138,"passed_time":36.07641933,"remaining_time":223.4661658,"test":[2.748966633]},
{"learn":[1.333677722],"iteration":139,"passed_time":36.38046023,"remaining_time":223.47997,"test":[2.728395498]},
{"learn":[1.323996841],"iteration":140,"passed_time":36.44703102,"remaining_time":222.0425507,"test":[2.709911706]},
{"learn":[1.315267528],"iteration":141,"passed_time":36.75911684,"remaining_time":222.1079032,"test":[2.68829898]},
{"learn":[1.306100762],"iteration":142,"passed_time":37.06634297,"remaining_time":222.1388526,"test":[2.673589224]},
{"learn":[1.297068194],"iteration":143,"passed_time":37.37299778,"remaining_time":222.161709,"test":[2.660972037]},
{"learn":[1.288901812],"iteration":144,"passed_time":37.68462959,"remaining_time":222.2093676,"test":[2.649648261]},
{"learn":[1.281763791],"iteration":145,"passed_time":37.99126144,"remaining_time":222.222858,"test":[2.628076599]},
{"learn":[1.274686616],"iteration":146,"passed_time":38.31391774,"remaining_time":222.3249785,"test":[2.612770086]},
{"learn":[1.267715344],"iteration":147,"passed_time":38.62102078,"remaining_time":222.3318223,"test":[2.59794893]},
{"learn":[1.260844832],"iteration":148,"passed_time":38.62706018,"remaining_time":220.6149545,"test":[2.57603176]},
{"learn":[1.253638384],"iteration":149,"passed_time":38.93119202,"remaining_time":220.6100881,"test":[2.566593582]},
{"learn":[1.247204221],"iteration":150,"passed_time":38.99926045,"remaining_time":219.2739876,"test":[2.555273279]},
{"learn":[1.241058394],"iteration":151,"passed_time":39.31111199,"remaining_time":219.3146248,"test":[2.542573357]},
{"learn":[1.235457343],"iteration":152,"passed_time":39.61442918,"remaining_time":219.3034086,"test":[2.531901049]},
{"learn":[1.229547333],"iteration":153,"passed_time":39.91636326,"remaining_time":219.2808008,"test":[2.520298482]},
{"learn":[1.225054409],"iteration":154,"passed_time":40.22425366,"remaining_time":219.2870603,"test":[2.507674781]},
{"learn":[1.2200119],"iteration":155,"passed_time":40.52688725,"remaining_time":219.2608515,"test":[2.487278452]},
{"learn":[1.215321393],"iteration":156,"passed_time":40.8483492,"remaining_time":219.3322189,"test":[2.477117428]},
{"learn":[1.210897241],"iteration":157,"passed_time":41.16325109,"remaining_time":219.3636545,"test":[2.468045303]},
{"learn":[1.206636353],"iteration":158,"passed_time":41.47558939,"remaining_time":219.3771741,"test":[2.45749733]},
{"learn":[1.201983759],"iteration":159,"passed_time":41.844191,"remaining_time":219.6820027,"test":[2.453683901]},
{"learn":[1.197968087],"iteration":160,"passed_time":42.20162754,"remaining_time":219.9202826,"test":[2.444521798]},
{"learn":[1.193717901],"iteration":161,"passed_time":42.52477314,"remaining_time":219.9738265,"test":[2.436662667]},
{"learn":[1.18949471],"iteration":162,"passed_time":42.83492545,"remaining_time":219.9560282,"test":[2.42857125]},
{"learn":[1.186353631],"iteration":163,"passed_time":43.14009867,"remaining_time":219.9092834,"test":[2.419298047]},
{"learn":[1.182456199],"iteration":164,"passed_time":43.4561486,"remaining_time":219.914449,"test":[2.419559589]},
{"learn":[1.179425907],"iteration":165,"passed_time":43.48993243,"remaining_time":218.4976124,"test":[2.409763274]},
{"learn":[1.176008714],"iteration":166,"passed_time":43.80208027,"remaining_time":218.4858256,"test":[2.405432998]},
{"learn":[1.173623402],"iteration":167,"passed_time":44.10657647,"remaining_time":218.4325692,"test":[2.394770456]},
{"learn":[1.17142089],"iteration":168,"passed_time":44.41137287,"remaining_time":218.3778157,"test":[2.384915213]},
{"learn":[1.16894048],"iteration":169,"passed_time":44.71432888,"remaining_time":218.3111351,"test":[2.376860862]},
{"learn":[1.166574628],"iteration":170,"passed_time":45.02167649,"remaining_time":218.2629813,"test":[2.368645835]},
{"learn":[1.164718451],"iteration":171,"passed_time":45.324814,"remaining_time":218.1915465,"test":[2.359904286]},
{"learn":[1.161717077],"iteration":172,"passed_time":45.63432625,"remaining_time":218.1479064,"test":[2.365854741]},
{"learn":[1.159662215],"iteration":173,"passed_time":45.94078066,"remaining_time":218.0866944,"test":[2.359923382]},
{"learn":[1.157426552],"iteration":174,"passed_time":46.23655616,"remaining_time":217.9723362,"test":[2.353476569]},
{"learn":[1.155365085],"iteration":175,"passed_time":46.25480186,"remaining_time":216.5565723,"test":[2.347300905]},
{"learn":[1.153363667],"iteration":176,"passed_time":46.56923114,"remaining_time":216.5337697,"test":[2.341415091]},
{"learn":[1.150902742],"iteration":177,"passed_time":46.70524075,"remaining_time":215.6837523,"test":[2.335233574]},
{"learn":[1.149167236],"iteration":178,"passed_time":47.02895734,"remaining_time":215.7026479,"test":[2.32628851]},
{"learn":[1.14676705],"iteration":179,"passed_time":47.06580193,"remaining_time":214.4108755,"test":[2.322250761]},
{"learn":[1.145124895],"iteration":180,"passed_time":47.37989985,"remaining_time":214.3875027,"test":[2.315568573]},
{"learn":[1.143228111],"iteration":181,"passed_time":47.6825075,"remaining_time":214.3092919,"test":[2.310328833]},
{"learn":[1.141198674],"iteration":182,"passed_time":47.9852656,"remaining_time":214.2293005,"test":[2.310830651]},
{"learn":[1.138946252],"iteration":183,"passed_time":48.27943096,"remaining_time":214.1087808,"test":[2.309949143]},
{"learn":[1.137621204],"iteration":184,"passed_time":48.574961,"remaining_time":213.9923958,"test":[2.305600629]},
{"learn":[1.135805802],"iteration":185,"passed_time":48.88096128,"remaining_time":213.9199058,"test":[2.301351808]},
{"learn":[1.133850106],"iteration":186,"passed_time":49.18554022,"remaining_time":213.838739,"test":[2.299016774]},
{"learn":[1.132066436],"iteration":187,"passed_time":49.49108804,"remaining_time":213.7593803,"test":[2.286690903]},
{"learn":[1.130495304],"iteration":188,"passed_time":49.79619952,"remaining_time":213.6757556,"test":[2.283446216]},
{"learn":[1.129282076],"iteration":189,"passed_time":50.10014848,"remaining_time":213.5848435,"test":[2.278546912]},
{"learn":[1.128164168],"iteration":190,"passed_time":50.45533945,"remaining_time":213.7087414,"test":[2.275429908]},
{"learn":[1.126738188],"iteration":191,"passed_time":50.77696007,"remaining_time":213.6863736,"test":[2.264267434]},
{"learn":[1.125444975],"iteration":192,"passed_time":51.08587545,"remaining_time":213.6077797,"test":[2.261872984]},
{"learn":[1.124620354],"iteration":193,"passed_time":51.38290745,"remaining_time":213.4774402,"test":[2.258361564]},
{"learn":[1.123574952],"iteration":194,"passed_time":51.69516515,"remaining_time":213.4082459,"test":[2.246496006]},
{"learn":[1.122508887],"iteration":195,"passed_time":52.00712295,"remaining_time":213.3353411,"test":[2.243304319]},
{"learn":[1.121549071],"iteration":196,"passed_time":52.14431587,"remaining_time":212.5476429,"test":[2.239916315]},
{"learn":[1.120703411],"iteration":197,"passed_time":52.19061006,"remaining_time":211.3983296,"test":[2.236368451]},
{"learn":[1.119435353],"iteration":198,"passed_time":52.22756722,"remaining_time":210.2225193,"test":[2.233427059]},
{"learn":[1.118747996],"iteration":199,"passed_time":52.53751749,"remaining_time":210.1500699,"test":[2.229956541]},
{"learn":[1.117764548],"iteration":200,"passed_time":52.84892795,"remaining_time":210.0810618,"test":[2.228329436]},
{"learn":[1.116991379],"iteration":201,"passed_time":52.98631439,"remaining_time":209.3221727,"test":[2.22579085]},
{"learn":[1.116596729],"iteration":202,"passed_time":53.31337895,"remaining_time":209.3141036,"test":[2.222237811]},
{"learn":[1.115982315],"iteration":203,"passed_time":53.62349843,"remaining_time":209.236788,"test":[2.219128174]},
{"learn":[1.115186418],"iteration":204,"passed_time":53.93830448,"remaining_time":209.1753759,"test":[2.213159311]},
{"learn":[1.114126207],"iteration":205,"passed_time":53.9480871,"remaining_time":207.9358309,"test":[2.212260039]},
{"learn":[1.11314406],"iteration":206,"passed_time":54.25434948,"remaining_time":207.8439572,"test":[2.210930548]},
{"learn":[1.112340451],"iteration":207,"passed_time":54.56177583,"remaining_time":207.7544541,"test":[2.208980195]},
{"learn":[1.111619834],"iteration":208,"passed_time":54.87527315,"remaining_time":207.6858424,"test":[2.206767836]},
{"learn":[1.111304524],"iteration":209,"passed_time":54.94174933,"remaining_time":206.6856284,"test":[2.203739665]},
{"learn":[1.110840395],"iteration":210,"passed_time":54.95242528,"remaining_time":205.4856092,"test":[2.201930862]},
{"learn":[1.110008588],"iteration":211,"passed_time":55.26181569,"remaining_time":205.4071262,"test":[2.200408566]},
{"learn":[1.109538593],"iteration":212,"passed_time":55.56437049,"remaining_time":205.3012187,"test":[2.198366316]},
{"learn":[1.109111903],"iteration":213,"passed_time":55.87067711,"remaining_time":205.2072533,"test":[2.196209846]},
{"learn":[1.108797659],"iteration":214,"passed_time":56.00699653,"remaining_time":204.4906618,"test":[2.194070167]},
{"learn":[1.107902671],"iteration":215,"passed_time":56.32300739,"remaining_time":204.4316564,"test":[2.192546667]},
{"learn":[1.107607118],"iteration":216,"passed_time":56.63134495,"remaining_time":204.3425949,"test":[2.190315631]},
{"learn":[1.106558156],"iteration":217,"passed_time":56.94103629,"remaining_time":204.2563779,"test":[2.188627626]},
{"learn":[1.106221704],"iteration":218,"passed_time":56.97550597,"remaining_time":203.1866218,"test":[2.186577729]},
{"learn":[1.105262972],"iteration":219,"passed_time":57.27988974,"remaining_time":203.0832454,"test":[2.186346987]},
{"learn":[1.104108866],"iteration":220,"passed_time":57.58095578,"remaining_time":202.9663554,"test":[2.188161258]},
{"learn":[1.103917641],"iteration":221,"passed_time":57.61649551,"remaining_time":201.917268,"test":[2.186402173]},
{"learn":[1.103655163],"iteration":222,"passed_time":57.93780599,"remaining_time":201.8729832,"test":[2.185180473]},
{"learn":[1.103066306],"iteration":223,"passed_time":58.24435244,"remaining_time":201.7750781,"test":[2.183355991]},
{"learn":[1.102535379],"iteration":224,"passed_time":58.27947311,"remaining_time":200.7404074,"test":[2.182431578]},
{"learn":[1.102134182],"iteration":225,"passed_time":58.31694816,"remaining_time":199.7226455,"test":[2.180941346]},
{"learn":[1.101695313],"iteration":226,"passed_time":58.38647122,"remaining_time":198.8226531,"test":[2.180408605]},
{"learn":[1.101325478],"iteration":227,"passed_time":58.70321821,"remaining_time":198.7670371,"test":[2.179055833]},
{"learn":[1.100905619],"iteration":228,"passed_time":59.00276408,"remaining_time":198.6512275,"test":[2.178116146]},
{"learn":[1.100676872],"iteration":229,"passed_time":59.00734461,"remaining_time":197.5463276,"test":[2.176608532]},
{"learn":[1.100391558],"iteration":230,"passed_time":59.31286119,"remaining_time":197.4527717,"test":[2.174838674]},
{"learn":[1.100026891],"iteration":231,"passed_time":59.61965408,"remaining_time":197.3616135,"test":[2.174611798]},
{"learn":[1.099409855],"iteration":232,"passed_time":59.65409953,"remaining_time":196.3720787,"test":[2.173337496]},
{"learn":[1.099108155],"iteration":233,"passed_time":59.69188867,"remaining_time":195.4016527,"test":[2.172771539]},
{"learn":[1.098937465],"iteration":234,"passed_time":60.00165185,"remaining_time":195.3245262,"test":[2.171704817]},
{"learn":[1.098393342],"iteration":235,"passed_time":60.31510972,"remaining_time":195.2573891,"test":[2.17097647]},
{"learn":[1.098303301],"iteration":236,"passed_time":60.45419832,"remaining_time":194.6268073,"test":[2.16963081]},
{"learn":[1.09807052],"iteration":237,"passed_time":60.4842331,"remaining_time":193.6512001,"test":[2.168644826]},
{"learn":[1.097695092],"iteration":238,"passed_time":60.79889859,"remaining_time":193.5897984,"test":[2.168791873]},
{"learn":[1.097295235],"iteration":239,"passed_time":61.10532951,"remaining_time":193.5002101,"test":[2.168338534]},
{"learn":[1.09723318],"iteration":240,"passed_time":61.13951065,"remaining_time":192.5514049,"test":[2.16708676]},
{"learn":[1.096842317],"iteration":241,"passed_time":61.45661594,"remaining_time":192.4963425,"test":[2.168218415]},
{"learn":[1.096740567],"iteration":242,"passed_time":61.7700582,"remaining_time":192.4277122,"test":[2.167041922]},
{"learn":[1.09645568],"iteration":243,"passed_time":62.06787174,"remaining_time":192.3086518,"test":[2.166093883]},
{"learn":[1.096268934],"iteration":244,"passed_time":62.07231853,"remaining_time":191.2840836,"test":[2.165929205]},
{"learn":[1.09577558],"iteration":245,"passed_time":62.37676826,"remaining_time":191.1873304,"test":[2.163786781]},
{"learn":[1.095602246],"iteration":246,"passed_time":62.44837961,"remaining_time":190.3790682,"test":[2.163007068]},
{"learn":[1.095439969],"iteration":247,"passed_time":62.46096489,"remaining_time":189.3977645,"test":[2.1622575]},
{"learn":[1.095358894],"iteration":248,"passed_time":62.7727851,"remaining_time":189.3267535,"test":[2.162182745]},
{"learn":[1.095150489],"iteration":249,"passed_time":62.80726562,"remaining_time":188.4217968,"test":[2.16151761]},
{"learn":[1.095125163],"iteration":250,"passed_time":62.8129823,"remaining_time":187.4379432,"test":[2.160638032]},
{"learn":[1.094944343],"iteration":251,"passed_time":62.82295693,"remaining_time":186.4744912,"test":[2.159823507]},
{"learn":[1.094776637],"iteration":252,"passed_time":63.13012386,"remaining_time":186.3960574,"test":[2.162304637]},
{"learn":[1.094515228],"iteration":253,"passed_time":63.43700996,"remaining_time":186.3149978,"test":[2.160654249]},
{"learn":[1.094454446],"iteration":254,"passed_time":63.44687622,"remaining_time":185.3644031,"test":[2.159077309]},
{"learn":[1.094223348],"iteration":255,"passed_time":63.75466073,"remaining_time":185.2869827,"test":[2.159443015]},
{"learn":[1.094198766],"iteration":256,"passed_time":63.76108111,"remaining_time":184.3365108,"test":[2.158417707]},
{"learn":[1.093999443],"iteration":257,"passed_time":64.07616218,"remaining_time":184.2810556,"test":[2.159106468]},
{"learn":[1.093946346],"iteration":258,"passed_time":64.14373351,"remaining_time":183.5154692,"test":[2.158275657]},
{"learn":[1.093828256],"iteration":259,"passed_time":64.15254185,"remaining_time":182.5880037,"test":[2.157789379]},
{"learn":[1.093702504],"iteration":260,"passed_time":64.1561014,"remaining_time":181.6527162,"test":[2.157193286]},
{"learn":[1.093583095],"iteration":261,"passed_time":64.46564765,"remaining_time":181.5864426,"test":[2.156541204]},
{"learn":[1.093435528],"iteration":262,"passed_time":64.60503836,"remaining_time":181.0414953,"test":[2.155978074]},
{"learn":[1.093307353],"iteration":263,"passed_time":64.62418265,"remaining_time":180.164388,"test":[2.155640437]},
{"learn":[1.093156908],"iteration":264,"passed_time":64.63097361,"remaining_time":179.2594929,"test":[2.156097844]},
{"learn":[1.093142892],"iteration":265,"passed_time":64.6342204,"remaining_time":178.3515706,"test":[2.155362665]},
{"learn":[1.093115406],"iteration":266,"passed_time":64.63880645,"remaining_time":177.4541016,"test":[2.154752545]},
{"learn":[1.093105408],"iteration":267,"passed_time":64.64170726,"remaining_time":176.558693,"test":[2.154243228]},
{"learn":[1.093092454],"iteration":268,"passed_time":64.64641684,"remaining_time":175.6748354,"test":[2.153663399]},
{"learn":[1.093080809],"iteration":269,"passed_time":64.64937113,"remaining_time":174.7927442,"test":[2.153119739]},
{"learn":[1.093069034],"iteration":270,"passed_time":64.65292838,"remaining_time":173.9187631,"test":[2.152634432]},
{"learn":[1.092980175],"iteration":271,"passed_time":64.6631408,"remaining_time":173.0689945,"test":[2.152520246]},
{"learn":[1.092970753],"iteration":272,"passed_time":64.66739715,"remaining_time":172.2095155,"test":[2.151956725]},
{"learn":[1.092878018],"iteration":273,"passed_time":64.67384581,"remaining_time":171.3620878,"test":[2.151508044]},
{"learn":[1.092865245],"iteration":274,"passed_time":64.67867628,"remaining_time":170.5165102,"test":[2.150935227]},
{"learn":[1.092855634],"iteration":275,"passed_time":64.68216117,"remaining_time":169.6734953,"test":[2.15038077]},
{"learn":[1.092849162],"iteration":276,"passed_time":64.68560257,"remaining_time":168.8364284,"test":[2.150052362]},
{"learn":[1.092837737],"iteration":277,"passed_time":64.68914774,"remaining_time":168.0056283,"test":[2.149589377]},
{"learn":[1.092831771],"iteration":278,"passed_time":64.69208587,"remaining_time":167.1791897,"test":[2.149125442]},
{"learn":[1.092812131],"iteration":279,"passed_time":64.71232064,"remaining_time":166.4031102,"test":[2.148698485]},
{"learn":[1.092806974],"iteration":280,"passed_time":64.71703884,"remaining_time":165.5927079,"test":[2.148262894]},
{"learn":[1.092784618],"iteration":281,"passed_time":64.72159408,"remaining_time":164.7876048,"test":[2.147861616]},
{"learn":[1.092766356],"iteration":282,"passed_time":64.72774746,"remaining_time":163.9922082,"test":[2.147690617]},
{"learn":[1.092753245],"iteration":283,"passed_time":64.73421998,"remaining_time":163.2031743,"test":[2.147834399]},
{"learn":[1.092688692],"iteration":284,"passed_time":64.7444458,"remaining_time":162.4290482,"test":[2.147577544]},
{"learn":[1.092685201],"iteration":285,"passed_time":64.7485835,"remaining_time":161.6450651,"test":[2.147277322]},
{"learn":[1.092583743],"iteration":286,"passed_time":64.75402214,"remaining_time":160.8697484,"test":[2.147129628]},
{"learn":[1.092580041],"iteration":287,"passed_time":64.75747265,"remaining_time":160.0948629,"test":[2.146723126]},
{"learn":[1.092557941],"iteration":288,"passed_time":64.82649143,"remaining_time":159.4866277,"test":[2.146203608]},
{"learn":[1.092549955],"iteration":289,"passed_time":64.83703566,"remaining_time":158.7389494,"test":[2.145846246]},
{"learn":[1.09254689],"iteration":290,"passed_time":64.84005004,"remaining_time":157.9779913,"test":[2.145545471]},
{"learn":[1.092540985],"iteration":291,"passed_time":64.84550794,"remaining_time":157.2281494,"test":[2.145257217]},
{"learn":[1.092536378],"iteration":292,"passed_time":64.85210803,"remaining_time":156.4861446,"test":[2.14496162]},
{"learn":[1.092533884],"iteration":293,"passed_time":64.85528002,"remaining_time":155.7409105,"test":[2.144642722]},
{"learn":[1.092528194],"iteration":294,"passed_time":64.85868351,"remaining_time":155.0012606,"test":[2.14437184]},
{"learn":[1.092472693],"iteration":295,"passed_time":64.89361362,"remaining_time":154.3415675,"test":[2.144583807]},
{"learn":[1.092414732],"iteration":296,"passed_time":64.90093408,"remaining_time":153.6207295,"test":[2.14465519]},
{"learn":[1.092396238],"iteration":297,"passed_time":64.90577687,"remaining_time":152.8988435,"test":[2.144476358]},
{"learn":[1.092380769],"iteration":298,"passed_time":64.97521543,"remaining_time":152.3331974,"test":[2.144370305]},
{"learn":[1.092378857],"iteration":299,"passed_time":64.98408865,"remaining_time":151.6295402,"test":[2.144090005]},
{"learn":[1.092365632],"iteration":300,"passed_time":64.9916758,"remaining_time":150.9275129,"test":[2.143713602]},
{"learn":[1.092363258],"iteration":301,"passed_time":64.99588502,"remaining_time":150.2222773,"test":[2.143471834]},
{"learn":[1.092355463],"iteration":302,"passed_time":65.00004497,"remaining_time":149.5215556,"test":[2.143184223]},
{"learn":[1.09235152],"iteration":303,"passed_time":65.00624275,"remaining_time":148.8300821,"test":[2.142914226]},
{"learn":[1.092349014],"iteration":304,"passed_time":65.00922454,"remaining_time":148.135774,"test":[2.14270865]},
{"learn":[1.092342899],"iteration":305,"passed_time":65.01494218,"remaining_time":147.4521891,"test":[2.142485331]},
{"learn":[1.092341169],"iteration":306,"passed_time":65.01878434,"remaining_time":146.7687868,"test":[2.142369566]},
{"learn":[1.092339868],"iteration":307,"passed_time":65.02247573,"remaining_time":146.0894585,"test":[2.142126904]},
{"learn":[1.092333273],"iteration":308,"passed_time":65.0272433,"remaining_time":145.4169098,"test":[2.14149485]},
{"learn":[1.092331175],"iteration":309,"passed_time":65.03118019,"remaining_time":144.7468204,"test":[2.14133673]},
{"learn":[1.092329612],"iteration":310,"passed_time":65.03497827,"remaining_time":144.0807075,"test":[2.141183339]},
{"learn":[1.092321808],"iteration":311,"passed_time":65.03946591,"remaining_time":143.4203607,"test":[2.141058284]},
{"learn":[1.092319901],"iteration":312,"passed_time":65.04344256,"remaining_time":142.7630832,"test":[2.140906008]},
{"learn":[1.092318181],"iteration":313,"passed_time":65.04733052,"remaining_time":142.109773,"test":[2.140600982]},
{"learn":[1.09231477],"iteration":314,"passed_time":65.05132419,"remaining_time":141.4608161,"test":[2.1404677]},
{"learn":[1.092311566],"iteration":315,"passed_time":65.05502054,"remaining_time":140.8152976,"test":[2.140311103]},
{"learn":[1.092310714],"iteration":316,"passed_time":65.05905501,"remaining_time":140.174557,"test":[2.140192914]},
{"learn":[1.092307094],"iteration":317,"passed_time":65.06488324,"remaining_time":139.5416678,"test":[2.140037823]},
{"learn":[1.092305582],"iteration":318,"passed_time":65.06940371,"remaining_time":138.9099183,"test":[2.139895465]},
{"learn":[1.092304564],"iteration":319,"passed_time":65.07306252,"remaining_time":138.2802579,"test":[2.13976326]},
{"learn":[1.092303599],"iteration":320,"passed_time":65.07626182,"remaining_time":137.6535258,"test":[2.139635012]},
{"learn":[1.092302251],"iteration":321,"passed_time":65.08000927,"remaining_time":137.0318208,"test":[2.139508818]},
{"learn":[1.09230138],"iteration":322,"passed_time":65.08244456,"remaining_time":136.4111919,"test":[2.13938817]},
{"learn":[1.092300555],"iteration":323,"passed_time":65.08577793,"remaining_time":135.7962527,"test":[2.139271133]},
{"learn":[1.092299497],"iteration":324,"passed_time":65.08940318,"remaining_time":135.1856835,"test":[2.139156051]},
{"learn":[1.092298314],"iteration":325,"passed_time":65.09308831,"remaining_time":134.5789617,"test":[2.139040075]},
{"learn":[1.09229148],"iteration":326,"passed_time":65.09600933,"remaining_time":133.9743556,"test":[2.138970229]},
{"learn":[1.092290781],"iteration":327,"passed_time":65.09828395,"remaining_time":133.3720939,"test":[2.138866622]},
{"learn":[1.09228983],"iteration":328,"passed_time":65.10127752,"remaining_time":132.774946,"test":[2.138764579]},
{"learn":[1.092289607],"iteration":329,"passed_time":65.10363453,"remaining_time":132.1801065,"test":[2.138678562]},
{"learn":[1.092288572],"iteration":330,"passed_time":65.10589866,"remaining_time":131.5886592,"test":[2.138582802]},
{"learn":[1.092287579],"iteration":331,"passed_time":65.10811419,"remaining_time":131.0006635,"test":[2.138489907]},
{"learn":[1.092286708],"iteration":332,"passed_time":65.11092502,"remaining_time":130.4173783,"test":[2.138399138]},
{"learn":[1.092285773],"iteration":333,"passed_time":65.1131872,"remaining_time":129.8364751,"test":[2.138311632]},
{"learn":[1.092284875],"iteration":334,"passed_time":65.11500131,"remaining_time":129.2581369,"test":[2.138226744]},
{"learn":[1.092284007],"iteration":335,"passed_time":65.11781465,"remaining_time":128.6852051,"test":[2.138139002]},
{"learn":[1.09228337],"iteration":336,"passed_time":65.11996342,"remaining_time":128.1143494,"test":[2.138080538]},
{"learn":[1.092282904],"iteration":337,"passed_time":65.1222131,"remaining_time":127.5470564,"test":[2.138003564]},
{"learn":[1.092280788],"iteration":338,"passed_time":65.12395397,"remaining_time":126.9821049,"test":[2.13791978]},
{"learn":[1.092280022],"iteration":339,"passed_time":65.1269154,"remaining_time":126.4228358,"test":[2.137845403]},
{"learn":[1.092279629],"iteration":340,"passed_time":65.12935869,"remaining_time":125.8658281,"test":[2.137775457]},
{"learn":[1.092278912],"iteration":341,"passed_time":65.13223143,"remaining_time":125.3128897,"test":[2.137705352]},
{"learn":[1.092277426],"iteration":342,"passed_time":65.13617336,"remaining_time":124.7652067,"test":[2.137632468]},
{"learn":[1.092276769],"iteration":343,"passed_time":65.13877239,"remaining_time":124.2181241,"test":[2.137567515]},
{"learn":[1.092276449],"iteration":344,"passed_time":65.14186164,"remaining_time":123.6751286,"test":[2.137505877]},
{"learn":[1.092275747],"iteration":345,"passed_time":65.14545823,"remaining_time":123.136213,"test":[2.137444575]},
{"learn":[1.092275133],"iteration":346,"passed_time":65.14847463,"remaining_time":122.5992909,"test":[2.137384254]},
{"learn":[1.092274852],"iteration":347,"passed_time":65.15075067,"remaining_time":122.0640501,"test":[2.137328082]},
{"learn":[1.092274307],"iteration":348,"passed_time":65.15292101,"remaining_time":121.5316664,"test":[2.137291642]},
{"learn":[1.092274043],"iteration":349,"passed_time":65.15484244,"remaining_time":121.0018503,"test":[2.137238432]},
{"learn":[1.092272711],"iteration":350,"passed_time":65.15764547,"remaining_time":120.4766721,"test":[2.137179369]},
{"learn":[1.092272176],"iteration":351,"passed_time":65.15985077,"remaining_time":119.9533616,"test":[2.137127713]},
{"learn":[1.092270901],"iteration":352,"passed_time":65.16262783,"remaining_time":119.4340516,"test":[2.137071964]},
{"learn":[1.092270405],"iteration":353,"passed_time":65.1651173,"remaining_time":118.917135,"test":[2.137023479]},
{"learn":[1.092269926],"iteration":354,"passed_time":65.16786671,"remaining_time":118.4035888,"test":[2.136975869]},
{"learn":[1.092269735],"iteration":355,"passed_time":65.17027656,"remaining_time":117.892298,"test":[2.136932104]},
{"learn":[1.092269695],"iteration":356,"passed_time":65.17242364,"remaining_time":117.3833849,"test":[2.136895844]},
{"learn":[1.092269248],"iteration":357,"passed_time":65.17466699,"remaining_time":116.8774754,"test":[2.136852523]},
{"learn":[1.092268616],"iteration":358,"passed_time":65.17750206,"remaining_time":116.3754285,"test":[2.136810952]},
{"learn":[1.092268187],"iteration":359,"passed_time":65.17968461,"remaining_time":115.8749949,"test":[2.136770113]},
{"learn":[1.092267775],"iteration":360,"passed_time":65.18187188,"remaining_time":115.37733,"test":[2.136730496]},
{"learn":[1.092267157],"iteration":361,"passed_time":65.18467844,"remaining_time":114.8834941,"test":[2.136692577]},
{"learn":[1.09226655],"iteration":362,"passed_time":65.18763464,"remaining_time":114.3926261,"test":[2.136655793]},
{"learn":[1.092266152],"iteration":363,"passed_time":65.1904948,"remaining_time":113.9042711,"test":[2.13661895]},
{"learn":[1.092265557],"iteration":364,"passed_time":65.19354738,"remaining_time":113.4189112,"test":[2.136584364]},
{"learn":[1.092265423],"iteration":365,"passed_time":65.19570124,"remaining_time":112.93463,"test":[2.136552263]},
{"learn":[1.092265049],"iteration":366,"passed_time":65.19825274,"remaining_time":112.4536621,"test":[2.136518915]},
{"learn":[1.092264686],"iteration":367,"passed_time":65.20113918,"remaining_time":111.9758695,"test":[2.136486074]},
{"learn":[1.092264339],"iteration":368,"passed_time":65.2033733,"remaining_time":111.4995354,"test":[2.136454696]},
{"learn":[1.092264004],"iteration":369,"passed_time":65.20579192,"remaining_time":111.0260781,"test":[2.136424258]},
{"learn":[1.092263421],"iteration":370,"passed_time":65.20871674,"remaining_time":110.5560184,"test":[2.136395495]},
{"learn":[1.092263097],"iteration":371,"passed_time":65.21085118,"remaining_time":110.0871359,"test":[2.136366783]},
{"learn":[1.092262052],"iteration":372,"passed_time":65.21362863,"remaining_time":109.6218369,"test":[2.136333357]},
{"learn":[1.092261033],"iteration":373,"passed_time":65.21650839,"remaining_time":109.1591825,"test":[2.136300931]},
{"learn":[1.092260457],"iteration":374,"passed_time":65.2194134,"remaining_time":108.6990223,"test":[2.136275859]},
{"learn":[1.092259979],"iteration":375,"passed_time":65.22158937,"remaining_time":108.2400845,"test":[2.136267695]},
{"learn":[1.092258985],"iteration":376,"passed_time":65.2247622,"remaining_time":107.7852171,"test":[2.136237376]},
{"learn":[1.092258706],"iteration":377,"passed_time":65.22698642,"remaining_time":107.3311787,"test":[2.136213417]},
{"learn":[1.092257748],"iteration":378,"passed_time":65.22985543,"remaining_time":106.8805811,"test":[2.136184722]},
{"learn":[1.092257489],"iteration":379,"passed_time":65.23285897,"remaining_time":106.4325594,"test":[2.136161947]},
{"learn":[1.092257238],"iteration":380,"passed_time":65.23571651,"remaining_time":105.9866365,"test":[2.136139854]},
{"learn":[1.092256664],"iteration":381,"passed_time":65.23853058,"remaining_time":105.5429631,"test":[2.136119785]},
{"learn":[1.092256648],"iteration":382,"passed_time":65.24089176,"remaining_time":105.1008622,"test":[2.136107595]},
{"learn":[1.092256085],"iteration":383,"passed_time":65.24369445,"remaining_time":104.6617598,"test":[2.136088491]},
{"learn":[1.09225584],"iteration":384,"passed_time":65.24555522,"remaining_time":104.2234194,"test":[2.13606889]},
{"learn":[1.092255603],"iteration":385,"passed_time":65.24767163,"remaining_time":103.7877471,"test":[2.136049876]},
{"learn":[1.092253015],"iteration":386,"passed_time":65.25106074,"remaining_time":103.3563313,"test":[2.136032499]},
{"learn":[1.092252124],"iteration":387,"passed_time":65.25393309,"remaining_time":102.9263068,"test":[2.136009117]},
{"learn":[1.092251913],"iteration":388,"passed_time":65.25680728,"remaining_time":102.4984814,"test":[2.135991526]},
{"learn":[1.092251893],"iteration":389,"passed_time":65.25922387,"remaining_time":102.0721194,"test":[2.135983063]},
{"learn":[1.092251688],"iteration":390,"passed_time":65.26141371,"remaining_time":101.6475728,"test":[2.135966542]},
{"learn":[1.09225113],"iteration":391,"passed_time":65.26435509,"remaining_time":101.2263467,"test":[2.135951657]},
{"learn":[1.092251111],"iteration":392,"passed_time":65.26622547,"remaining_time":100.8055951,"test":[2.135944334]},
{"learn":[1.092250657],"iteration":393,"passed_time":65.26853547,"remaining_time":100.3876459,"test":[2.135944765]},
{"learn":[1.092250456],"iteration":394,"passed_time":65.27068227,"remaining_time":99.97155133,"test":[2.135929579]},
{"learn":[1.092250261],"iteration":395,"passed_time":65.27299903,"remaining_time":99.5578066,"test":[2.135914847]},
{"learn":[1.092250241],"iteration":396,"passed_time":65.27472743,"remaining_time":99.14524091,"test":[2.135908809]},
{"learn":[1.092250051],"iteration":397,"passed_time":65.27778116,"remaining_time":98.73674437,"test":[2.135894385]},
{"learn":[1.092249211],"iteration":398,"passed_time":65.2805736,"remaining_time":98.32988655,"test":[2.135875345]},
{"learn":[1.092249036],"iteration":399,"passed_time":65.28286417,"remaining_time":97.92429625,"test":[2.135862218]},
{"learn":[1.092248867],"iteration":400,"passed_time":65.28529619,"remaining_time":97.52092872,"test":[2.135849485]},
{"learn":[1.092248841],"iteration":401,"passed_time":65.28751219,"remaining_time":97.11923455,"test":[2.135845401]},
{"learn":[1.092248032],"iteration":402,"passed_time":65.29030427,"remaining_time":96.7203763,"test":[2.135827855]},
{"learn":[1.092247873],"iteration":403,"passed_time":65.29270812,"remaining_time":96.32290604,"test":[2.135816145]},
{"learn":[1.092247844],"iteration":404,"passed_time":65.29506003,"remaining_time":95.92731041,"test":[2.135813058]},
{"learn":[1.092247816],"iteration":405,"passed_time":65.29724209,"remaining_time":95.53340345,"test":[2.135810064]},
{"learn":[1.092247789],"iteration":406,"passed_time":65.29906928,"remaining_time":95.14090438,"test":[2.135807159]},
{"learn":[1.092247764],"iteration":407,"passed_time":65.30164399,"remaining_time":94.751405,"test":[2.135804342]},
{"learn":[1.092247604],"iteration":408,"passed_time":65.30337463,"remaining_time":94.36257801,"test":[2.135793481]},
{"learn":[1.09224745],"iteration":409,"passed_time":65.30556002,"remaining_time":93.97629368,"test":[2.135782945]},
{"learn":[1.092247423],"iteration":410,"passed_time":65.30731525,"remaining_time":93.59126199,"test":[2.135780852]},
{"learn":[1.092247396],"iteration":411,"passed_time":65.30943961,"remaining_time":93.20861769,"test":[2.135778822]},
{"learn":[1.092246835],"iteration":412,"passed_time":65.31230849,"remaining_time":92.8288743,"test":[2.135769736]},
{"learn":[1.092246044],"iteration":413,"passed_time":65.31516158,"remaining_time":92.45092919,"test":[2.135754599]},
{"learn":[1.092245896],"iteration":414,"passed_time":65.31697185,"remaining_time":92.07332177,"test":[2.13574524]},
{"learn":[1.092245868],"iteration":415,"passed_time":65.31893285,"remaining_time":91.69773265,"test":[2.135744222]},
{"learn":[1.092245724],"iteration":416,"passed_time":65.32102319,"remaining_time":91.32411636,"test":[2.135735211]},
{"learn":[1.092245696],"iteration":417,"passed_time":65.32311645,"remaining_time":90.95228175,"test":[2.135734493]},
{"learn":[1.092245554],"iteration":418,"passed_time":65.3252726,"remaining_time":90.58229924,"test":[2.13572581]},
{"learn":[1.092244794],"iteration":419,"passed_time":65.32800314,"remaining_time":90.21486148,"test":[2.135712047]},
{"learn":[1.092244763],"iteration":420,"passed_time":65.33020903,"remaining_time":89.84843475,"test":[2.135712022]},
{"learn":[1.09224463],"iteration":421,"passed_time":65.33249441,"remaining_time":89.48384305,"test":[2.135704011]},
{"learn":[1.092244502],"iteration":422,"passed_time":65.33482615,"remaining_time":89.12102763,"test":[2.135696239]},
{"learn":[1.092244469],"iteration":423,"passed_time":65.33759991,"remaining_time":88.76051309,"test":[2.135696687]},
{"learn":[1.092244344],"iteration":424,"passed_time":65.33974427,"remaining_time":88.40083048,"test":[2.135689175]},
{"learn":[1.092244311],"iteration":425,"passed_time":65.34226163,"remaining_time":88.04332905,"test":[2.135689835]},
{"learn":[1.092241913],"iteration":426,"passed_time":65.34569043,"remaining_time":87.68871339,"test":[2.135683413]},
{"learn":[1.092241796],"iteration":427,"passed_time":65.3481306,"remaining_time":87.33441752,"test":[2.135676296]},
{"learn":[1.092241718],"iteration":428,"passed_time":65.35033307,"remaining_time":86.98144564,"test":[2.135668992]},
{"learn":[1.092241607],"iteration":429,"passed_time":65.35283988,"remaining_time":86.63050867,"test":[2.135662244]},
{"learn":[1.092241499],"iteration":430,"passed_time":65.35472065,"remaining_time":86.28036206,"test":[2.135655698]},
{"learn":[1.092241459],"iteration":431,"passed_time":65.35688782,"remaining_time":85.93220435,"test":[2.135657282]},
{"learn":[1.092241354],"iteration":432,"passed_time":65.35904928,"remaining_time":85.58563728,"test":[2.13565093]},
{"learn":[1.092241313],"iteration":433,"passed_time":65.36129251,"remaining_time":85.24076397,"test":[2.135652656]},
{"learn":[1.092241275],"iteration":434,"passed_time":65.36348123,"remaining_time":84.89739517,"test":[2.135654331]},
{"learn":[1.092238939],"iteration":435,"passed_time":65.36698988,"remaining_time":84.55729884,"test":[2.135648946]},
{"learn":[1.092238901],"iteration":436,"passed_time":65.36929819,"remaining_time":84.21719653,"test":[2.135650679]},
{"learn":[1.092238799],"iteration":437,"passed_time":65.37180218,"remaining_time":83.87888773,"test":[2.135644617]},
{"learn":[1.0922387],"iteration":438,"passed_time":65.37394032,"remaining_time":83.54164128,"test":[2.135638737]},
{"learn":[1.092238605],"iteration":439,"passed_time":65.37602841,"remaining_time":83.20585435,"test":[2.135633033]},
{"learn":[1.092238513],"iteration":440,"passed_time":65.37823717,"remaining_time":82.87173374,"test":[2.135627499]},
{"learn":[1.09223847],"iteration":441,"passed_time":65.38035047,"remaining_time":82.53899449,"test":[2.135629874]},
{"learn":[1.092238379],"iteration":442,"passed_time":65.38247428,"remaining_time":82.20776112,"test":[2.135624482]},
{"learn":[1.092238336],"iteration":443,"passed_time":65.38473253,"remaining_time":81.87817857,"test":[2.135626947]},
{"learn":[1.092238295],"iteration":444,"passed_time":65.38718865,"remaining_time":81.55031394,"test":[2.135629338]},
{"learn":[1.092238205],"iteration":445,"passed_time":65.38949076,"remaining_time":81.22371722,"test":[2.135624054]},
{"learn":[1.092238164],"iteration":446,"passed_time":65.39123582,"remaining_time":80.89788234,"test":[2.135626532]},
{"learn":[1.092237728],"iteration":447,"passed_time":65.39342266,"remaining_time":80.57403863,"test":[2.135634994]},
{"learn":[1.092237689],"iteration":448,"passed_time":65.39559865,"remaining_time":80.25161438,"test":[2.135637326]},
{"learn":[1.092237652],"iteration":449,"passed_time":65.39785451,"remaining_time":79.93071107,"test":[2.135639588]},
{"learn":[1.092237616],"iteration":450,"passed_time":65.40011699,"remaining_time":79.61122888,"test":[2.135641782]},
{"learn":[1.092236912],"iteration":451,"passed_time":65.40317517,"remaining_time":79.29411504,"test":[2.135631122]},
{"learn":[1.092236875],"iteration":452,"passed_time":65.40565929,"remaining_time":78.97769455,"test":[2.13563357]},
{"learn":[1.09223684],"iteration":453,"passed_time":65.40792038,"remaining_time":78.66238882,"test":[2.135635944]},
{"learn":[1.092234513],"iteration":454,"passed_time":65.41065449,"remaining_time":78.34902571,"test":[2.135631291]},
{"learn":[1.092233827],"iteration":455,"passed_time":65.41357813,"remaining_time":78.0372511,"test":[2.135620978]},
{"learn":[1.092233743],"iteration":456,"passed_time":65.41587096,"remaining_time":77.72607862,"test":[2.135616243]},
{"learn":[1.091782207],"iteration":457,"passed_time":65.72146006,"remaining_time":77.77517762,"test":[2.1367502]},
{"learn":[1.091782124],"iteration":458,"passed_time":65.72375442,"remaining_time":77.46525304,"test":[2.136744327]},
{"learn":[1.091769684],"iteration":459,"passed_time":65.79124155,"remaining_time":77.2331966,"test":[2.136709285]},
{"learn":[1.091744584],"iteration":460,"passed_time":65.80725402,"remaining_time":76.9416701,"test":[2.136861742]},
{"learn":[1.091744508],"iteration":461,"passed_time":65.8098274,"remaining_time":76.63568646,"test":[2.136855426]},
{"learn":[1.091744463],"iteration":462,"passed_time":65.8117835,"remaining_time":76.33029749,"test":[2.136856755]},
{"learn":[1.091744419],"iteration":463,"passed_time":65.8139955,"remaining_time":76.02651204,"test":[2.136858045]},
{"learn":[1.091676321],"iteration":464,"passed_time":65.84795669,"remaining_time":75.76055232,"test":[2.136907908]},
{"learn":[1.090621786],"iteration":465,"passed_time":66.15226319,"remaining_time":75.80538314,"test":[2.140125389]},
{"learn":[1.090584177],"iteration":466,"passed_time":66.15831574,"remaining_time":75.50831326,"test":[2.139844097]},
{"learn":[1.089753817],"iteration":467,"passed_time":66.46545275,"remaining_time":75.55474543,"test":[2.142281759]},
{"learn":[1.089753737],"iteration":468,"passed_time":66.46767363,"remaining_time":75.25444499,"test":[2.142270714]},
{"learn":[1.088862557],"iteration":469,"passed_time":66.78280485,"remaining_time":75.3082693,"test":[2.143128528]},
{"learn":[1.08883862],"iteration":470,"passed_time":66.85044611,"remaining_time":75.0825605,"test":[2.14325193]},
{"learn":[1.088838566],"iteration":471,"passed_time":66.85853918,"remaining_time":74.79090823,"test":[2.143245281]},
{"learn":[1.088838488],"iteration":472,"passed_time":66.86134749,"remaining_time":74.49456687,"test":[2.143230766]},
{"learn":[1.088838435],"iteration":473,"passed_time":66.86355518,"remaining_time":74.19879752,"test":[2.143224746]},
{"learn":[1.088837765],"iteration":474,"passed_time":66.86633798,"remaining_time":73.90489987,"test":[2.143206215]},
{"learn":[1.088837693],"iteration":475,"passed_time":66.86882805,"remaining_time":73.61190314,"test":[2.143193346]},
{"learn":[1.088791975],"iteration":476,"passed_time":66.88660464,"remaining_time":73.33688517,"test":[2.143314811]},
{"learn":[1.087911153],"iteration":477,"passed_time":67.19234162,"remaining_time":73.37741072,"test":[2.145859271]},
{"learn":[1.087911092],"iteration":478,"passed_time":67.19458724,"remaining_time":73.08638821,"test":[2.145851559]},
{"learn":[1.087910433],"iteration":479,"passed_time":67.19749753,"remaining_time":72.79728899,"test":[2.14583141]},
{"learn":[1.087910367],"iteration":480,"passed_time":67.19995628,"remaining_time":72.50889253,"test":[2.145816899]},
{"learn":[1.087910304],"iteration":481,"passed_time":67.20223693,"remaining_time":72.22149115,"test":[2.145810456]},
{"learn":[1.087910244],"iteration":482,"passed_time":67.20404556,"remaining_time":71.93476512,"test":[2.145804205]},
{"learn":[1.087846156],"iteration":483,"passed_time":67.50067627,"remaining_time":71.9635309,"test":[2.145637503]},
{"learn":[1.087845512],"iteration":484,"passed_time":67.50343391,"remaining_time":71.67890404,"test":[2.145621325]},
{"learn":[1.087845451],"iteration":485,"passed_time":67.5054232,"remaining_time":71.39462453,"test":[2.145610645]},
{"learn":[1.087821362],"iteration":486,"passed_time":67.52303607,"remaining_time":71.12796202,"test":[2.145703087]},
{"learn":[1.087821304],"iteration":487,"passed_time":67.52688089,"remaining_time":70.84787503,"test":[2.145693421]},
{"learn":[1.087820682],"iteration":488,"passed_time":67.52988203,"remaining_time":70.56803624,"test":[2.145679036]},
{"learn":[1.087820628],"iteration":489,"passed_time":67.53286565,"remaining_time":70.28930915,"test":[2.145669666]},
{"learn":[1.087820577],"iteration":490,"passed_time":67.53522366,"remaining_time":70.01105671,"test":[2.145660955]},
{"learn":[1.087808224],"iteration":491,"passed_time":67.56920264,"remaining_time":69.76657508,"test":[2.145751893]},
{"learn":[1.087765594],"iteration":492,"passed_time":67.88157005,"remaining_time":69.80924141,"test":[2.145653055]},
{"learn":[1.087764989],"iteration":493,"passed_time":67.88508158,"remaining_time":69.5341119,"test":[2.145642163]},
{"learn":[1.087697018],"iteration":494,"passed_time":68.18363803,"remaining_time":69.56108526,"test":[2.145625118]},
{"learn":[1.087696971],"iteration":495,"passed_time":68.18597361,"remaining_time":69.28574738,"test":[2.145619935]},
{"learn":[1.087696381],"iteration":496,"passed_time":68.1888553,"remaining_time":69.01206079,"test":[2.145609964]},
{"learn":[1.087689495],"iteration":497,"passed_time":68.19343848,"remaining_time":68.74117695,"test":[2.145473535]},
{"learn":[1.087689452],"iteration":498,"passed_time":68.19588082,"remaining_time":68.46921101,"test":[2.145468977]},
{"learn":[1.087620203],"iteration":499,"passed_time":68.2137279,"remaining_time":68.2137279,"test":[2.145773908]},
{"learn":[1.087589262],"iteration":500,"passed_time":68.21964118,"remaining_time":67.94730728,"test":[2.146043808]},
{"learn":[1.087589219],"iteration":501,"passed_time":68.22211696,"remaining_time":67.67851443,"test":[2.146037511]},
{"learn":[1.087589142],"iteration":502,"passed_time":68.22459719,"remaining_time":67.4107849,"test":[2.146039067]},
{"learn":[1.087589099],"iteration":503,"passed_time":68.22685694,"remaining_time":67.14389096,"test":[2.146032974]},
{"learn":[1.087589024],"iteration":504,"passed_time":68.2290211,"remaining_time":66.87795137,"test":[2.146034666]},
{"learn":[1.087588981],"iteration":505,"passed_time":68.23118404,"remaining_time":66.61305319,"test":[2.146028765]},
{"learn":[1.087588965],"iteration":506,"passed_time":68.23335503,"remaining_time":66.34919927,"test":[2.146017378]},
{"learn":[1.087588923],"iteration":507,"passed_time":68.23550884,"remaining_time":66.08635896,"test":[2.146011753]},
{"learn":[1.087588849],"iteration":508,"passed_time":68.23774005,"remaining_time":65.82461762,"test":[2.146013845]},
{"learn":[1.087588807],"iteration":509,"passed_time":68.23988598,"remaining_time":65.56381202,"test":[2.146008385]},
{"learn":[1.087588767],"iteration":510,"passed_time":68.24210898,"remaining_time":65.30409254,"test":[2.14600309]},
{"learn":[1.087588728],"iteration":511,"passed_time":68.24429089,"remaining_time":65.04533975,"test":[2.145997952]},
{"learn":[1.087556827],"iteration":512,"passed_time":68.27847962,"remaining_time":64.81797188,"test":[2.145670979]},
{"learn":[1.087556751],"iteration":513,"passed_time":68.28358067,"remaining_time":64.56385254,"test":[2.1456738]},
{"learn":[1.087556678],"iteration":514,"passed_time":68.28574839,"remaining_time":64.3079378,"test":[2.145676537]},
{"learn":[1.0875471],"iteration":515,"passed_time":68.29031621,"remaining_time":64.05525784,"test":[2.145401468]},
{"learn":[1.08754706],"iteration":516,"passed_time":68.29269878,"remaining_time":63.80149615,"test":[2.145396972]},
{"learn":[1.086647871],"iteration":517,"passed_time":68.6010895,"remaining_time":63.83344621,"test":[2.147408097]},
{"learn":[1.086647799],"iteration":518,"passed_time":68.60395292,"remaining_time":63.58092746,"test":[2.147406831]},
{"learn":[1.086647758],"iteration":519,"passed_time":68.60589895,"remaining_time":63.32852211,"test":[2.147398264]},
{"learn":[1.086647717],"iteration":520,"passed_time":68.60806974,"remaining_time":63.07728484,"test":[2.147389953]},
{"learn":[1.086647679],"iteration":521,"passed_time":68.61021361,"remaining_time":62.82697721,"test":[2.147381891]},
{"learn":[1.086647101],"iteration":522,"passed_time":68.61307976,"remaining_time":62.57827733,"test":[2.147369096]},
{"learn":[1.086647025],"iteration":523,"passed_time":68.61534558,"remaining_time":62.32997041,"test":[2.147368997]},
{"learn":[1.086646988],"iteration":524,"passed_time":68.61762244,"remaining_time":62.08261078,"test":[2.147361586]},
{"learn":[1.086646946],"iteration":525,"passed_time":68.62053792,"remaining_time":61.83675851,"test":[2.14734864]},
{"learn":[1.086634313],"iteration":526,"passed_time":68.65427907,"remaining_time":61.61949526,"test":[2.147299353]},
{"learn":[1.086634237],"iteration":527,"passed_time":68.65952513,"remaining_time":61.37745428,"test":[2.147300461]},
{"learn":[1.086546465],"iteration":528,"passed_time":68.96357555,"remaining_time":61.40235176,"test":[2.147476807]},
{"learn":[1.086531454],"iteration":529,"passed_time":68.99750523,"remaining_time":61.1864669,"test":[2.147418339]},
{"learn":[1.086531418],"iteration":530,"passed_time":69.00446971,"remaining_time":60.94745065,"test":[2.147411781]},
{"learn":[1.086524947],"iteration":531,"passed_time":69.01061707,"remaining_time":60.70858795,"test":[2.147517532]},
{"learn":[1.085987585],"iteration":532,"passed_time":69.31432412,"remaining_time":60.73131213,"test":[2.149902475]},
{"learn":[1.08595974],"iteration":533,"passed_time":69.32429494,"remaining_time":60.4964821,"test":[2.150051546]},
{"learn":[1.085959182],"iteration":534,"passed_time":69.32799742,"remaining_time":60.25704449,"test":[2.150036593]},
{"learn":[1.085959147],"iteration":535,"passed_time":69.33024475,"remaining_time":60.0172268,"test":[2.150026955]},
{"learn":[1.085216004],"iteration":536,"passed_time":69.63840752,"remaining_time":60.04205341,"test":[2.15121112]},
{"learn":[1.085172038],"iteration":537,"passed_time":69.65673737,"remaining_time":59.81675216,"test":[2.151335541]},
{"learn":[1.084555528],"iteration":538,"passed_time":69.9619917,"remaining_time":59.83762184,"test":[2.153188773]},
{"learn":[1.084550205],"iteration":539,"passed_time":69.96536407,"remaining_time":59.60012495,"test":[2.152962454]},
{"learn":[1.084295139],"iteration":540,"passed_time":70.27198322,"remaining_time":59.62077689,"test":[2.153372129]},
{"learn":[1.084295103],"iteration":541,"passed_time":70.27429064,"remaining_time":59.38307216,"test":[2.153357756]},
{"learn":[1.084295067],"iteration":542,"passed_time":70.2764979,"remaining_time":59.14615017,"test":[2.153343813]},
{"learn":[1.084202959],"iteration":543,"passed_time":70.58440118,"remaining_time":59.16633628,"test":[2.153169991]},
{"learn":[1.084202924],"iteration":544,"passed_time":70.5866488,"remaining_time":58.93013799,"test":[2.153155706]},
{"learn":[1.084202891],"iteration":545,"passed_time":70.588911,"remaining_time":58.69480878,"test":[2.153141849]},
{"learn":[1.084141621],"iteration":546,"passed_time":70.89925696,"remaining_time":58.7154724,"test":[2.152973013]},
{"learn":[1.084128297],"iteration":547,"passed_time":70.903976,"remaining_time":58.48284151,"test":[2.153269334]},
{"learn":[1.084127747],"iteration":548,"passed_time":70.90689125,"remaining_time":58.24955912,"test":[2.153252916]},
{"learn":[1.08412772],"iteration":549,"passed_time":70.90923545,"remaining_time":58.01664719,"test":[2.153241762]},
{"learn":[1.084127693],"iteration":550,"passed_time":70.91137544,"remaining_time":57.78440576,"test":[2.153230943]},
{"learn":[1.084127668],"iteration":551,"passed_time":70.91325713,"remaining_time":57.5527884,"test":[2.153220447]},
{"learn":[1.084127567],"iteration":552,"passed_time":70.91557213,"remaining_time":57.32235215,"test":[2.153217852]},
{"learn":[1.084127542],"iteration":553,"passed_time":70.91786553,"remaining_time":57.09272207,"test":[2.153207817]},
{"learn":[1.083596185],"iteration":554,"passed_time":71.22204562,"remaining_time":57.1059645,"test":[2.154630925]},
{"learn":[1.083596155],"iteration":555,"passed_time":71.22424536,"remaining_time":56.87691536,"test":[2.154617444]},
{"learn":[1.083567737],"iteration":556,"passed_time":71.36076741,"remaining_time":56.7555116,"test":[2.154465012]},
{"learn":[1.08356771],"iteration":557,"passed_time":71.37501811,"remaining_time":56.53720072,"test":[2.154452221]},
{"learn":[1.083567685],"iteration":558,"passed_time":71.37725074,"remaining_time":56.31013878,"test":[2.154439813]},
{"learn":[1.082774424],"iteration":559,"passed_time":71.67929013,"remaining_time":56.31944225,"test":[2.155344035]},
{"learn":[1.082767776],"iteration":560,"passed_time":71.6827807,"remaining_time":56.09401199,"test":[2.155464589]},
{"learn":[1.082710482],"iteration":561,"passed_time":71.98931379,"remaining_time":56.10555061,"test":[2.155455974]},
{"learn":[1.082710463],"iteration":562,"passed_time":71.99179579,"remaining_time":55.87995517,"test":[2.155448451]},
{"learn":[1.082698818],"iteration":563,"passed_time":72.00168164,"remaining_time":55.66087446,"test":[2.155577474]},
{"learn":[1.0826988],"iteration":564,"passed_time":72.00475621,"remaining_time":55.43729018,"test":[2.155570484]},
{"learn":[1.082680235],"iteration":565,"passed_time":72.07159688,"remaining_time":55.26337994,"test":[2.15564392]},
{"learn":[1.082680219],"iteration":566,"passed_time":72.07977876,"remaining_time":55.04505151,"test":[2.155637921]},
{"learn":[1.082680203],"iteration":567,"passed_time":72.08196038,"remaining_time":54.82289944,"test":[2.155632101]},
{"learn":[1.082680188],"iteration":568,"passed_time":72.08411836,"remaining_time":54.60150266,"test":[2.155626456]},
{"learn":[1.082680173],"iteration":569,"passed_time":72.08636447,"remaining_time":54.38094161,"test":[2.15562098]},
{"learn":[1.082680159],"iteration":570,"passed_time":72.08858634,"remaining_time":54.16112704,"test":[2.155615667]},
{"learn":[1.08267965],"iteration":571,"passed_time":72.09151224,"remaining_time":53.94260007,"test":[2.155605784]},
{"learn":[1.082135513],"iteration":572,"passed_time":72.39109695,"remaining_time":53.94589598,"test":[2.156612593]},
{"learn":[1.082135503],"iteration":573,"passed_time":72.3934654,"remaining_time":53.72755446,"test":[2.156607912]},
{"learn":[1.082135493],"iteration":574,"passed_time":72.395652,"remaining_time":53.50982974,"test":[2.156603372]},
{"learn":[1.082135005],"iteration":575,"passed_time":72.39850984,"remaining_time":53.29334752,"test":[2.156594333]},
{"learn":[1.082134527],"iteration":576,"passed_time":72.4016155,"remaining_time":53.07778745,"test":[2.156585564]},
{"learn":[1.082134519],"iteration":577,"passed_time":72.40380547,"remaining_time":52.86229396,"test":[2.156581623]},
{"learn":[1.082134511],"iteration":578,"passed_time":72.4056123,"remaining_time":52.64725869,"test":[2.156577799]},
{"learn":[1.08212878],"iteration":579,"passed_time":72.40912496,"remaining_time":52.43419394,"test":[2.156369364]},
{"learn":[1.082128772],"iteration":580,"passed_time":72.41203898,"remaining_time":52.22141881,"test":[2.1563653]},
{"learn":[1.082123852],"iteration":581,"passed_time":72.41651646,"remaining_time":52.01048777,"test":[2.156163213]},
{"learn":[1.082123845],"iteration":582,"passed_time":72.41889382,"remaining_time":51.79876282,"test":[2.156159614]},
{"learn":[1.081530574],"iteration":583,"passed_time":72.72209582,"remaining_time":51.80204086,"test":[2.153651293]},
{"learn":[1.081523164],"iteration":584,"passed_time":72.7281888,"remaining_time":51.59350145,"test":[2.153749729]},
{"learn":[1.081523157],"iteration":585,"passed_time":72.7307542,"remaining_time":51.38316081,"test":[2.153744653]},
{"learn":[1.081523151],"iteration":586,"passed_time":72.73300564,"remaining_time":51.1733072,"test":[2.153739729]},
{"learn":[1.081514941],"iteration":587,"passed_time":72.74307392,"remaining_time":50.96963683,"test":[2.153696354]},
{"learn":[1.081514935],"iteration":588,"passed_time":72.745738,"remaining_time":50.76145724,"test":[2.153692125]},
{"learn":[1.081508545],"iteration":589,"passed_time":72.75020549,"remaining_time":50.55522755,"test":[2.153809235]},
{"learn":[1.08150854],"iteration":590,"passed_time":72.75315067,"remaining_time":50.34862712,"test":[2.153804762]},
{"learn":[1.081508535],"iteration":591,"passed_time":72.75504658,"remaining_time":50.14199156,"test":[2.153800618]},
{"learn":[1.081399736],"iteration":592,"passed_time":72.7728963,"remaining_time":49.94699628,"test":[2.153811783]},
{"learn":[1.081399731],"iteration":593,"passed_time":72.77735881,"remaining_time":49.74344727,"test":[2.153806012]},
{"learn":[1.081399726],"iteration":594,"passed_time":72.77951048,"remaining_time":49.53899453,"test":[2.153800603]},
{"learn":[1.081399722],"iteration":595,"passed_time":72.78171715,"remaining_time":49.33525793,"test":[2.153795355]},
{"learn":[1.081399718],"iteration":596,"passed_time":72.78390558,"remaining_time":49.13218417,"test":[2.153790264]},
{"learn":[1.081399714],"iteration":597,"passed_time":72.78634552,"remaining_time":48.92995133,"test":[2.153785326]},
{"learn":[1.08139971],"iteration":598,"passed_time":72.78876434,"remaining_time":48.72837145,"test":[2.153780535]},
{"learn":[1.081399706],"iteration":599,"passed_time":72.79172354,"remaining_time":48.5278157,"test":[2.153775699]},
{"learn":[1.081399702],"iteration":600,"passed_time":72.79449951,"remaining_time":48.32779585,"test":[2.153771009]},
{"learn":[1.081399699],"iteration":601,"passed_time":72.79676557,"remaining_time":48.12809418,"test":[2.153766639]},
{"learn":[1.081327625],"iteration":602,"passed_time":72.80302456,"remaining_time":47.93167621,"test":[2.152844921]},
{"learn":[1.081327622],"iteration":603,"passed_time":72.80516985,"remaining_time":47.73319083,"test":[2.152841735]},
{"learn":[1.081327619],"iteration":604,"passed_time":72.8073056,"remaining_time":47.53534829,"test":[2.152838645]},
{"learn":[1.081276813],"iteration":605,"passed_time":73.11705845,"remaining_time":47.53815352,"test":[2.152639749]},
{"learn":[1.08127681],"iteration":606,"passed_time":73.11951873,"remaining_time":47.34097341,"test":[2.152637872]}
]}